sakdas/Analyst.py
sakdas/Auditor.py
sakdas/Commander.py
sakdas/DataQualityMetric.py
sakdas/Sakdas.py
sakdas/Selector.py
sakdas/Visualizer copy.py
sakdas/Visualizer.py
sakdas/__init__.py
sakdas/buildAnalyst.py
sakdas/dataQualityConfig.json
sakdas/test.py
sakdas/testCase.py
sakdas/html_template/template_auditing_report.html
sakdas/html_template/template_column_profile.html
sakdas/html_template/template_column_profile_int.html
sakdas/html_template/template_column_profile_obj.html
sakdas/html_template/template_full_report.html
sakdas/html_template/template_report_header.html
sakdas-4.0.16.dist-info/LICENSE
sakdas-4.0.16.dist-info/METADATA
sakdas-4.0.16.dist-info/WHEEL
sakdas-4.0.16.dist-info/top_level.txt
sakdas-4.0.16.dist-info/RECORD
