Metadata-Version: 2.1
Name: sakdas
Version: 4.0.16
Summary: A data profiling and data quality auditing
Home-page: https://github.com/sakdaloe/sakdas
Author: Sakda Loetpipatwanich
Author-email: sakda.loet@gmail.com
License: UNKNOWN
Platform: UNKNOWN
Classifier: Programming Language :: Python :: 3
Classifier: License :: OSI Approved :: BSD License
Classifier: Operating System :: OS Independent
Requires-Python: >=3.6
